{"data":{"className":"BaseEntity","properties":{"id":{"name":"id","reference":"scalar","primary":true,"type":"number"},"idx":{"name":"idx","reference":"scalar","defaultRaw":"uuid_generate_v4()","getter":false,"setter":false,"type":"string"},"is_active":{"name":"is_active","reference":"scalar","nullable":false,"default":true,"getter":false,"setter":false,"type":"boolean"},"is_obsolete":{"name":"is_obsolete","reference":"scalar","nullable":false,"default":false,"getter":false,"setter":false,"type":"boolean"},"createdAt":{"name":"createdAt","reference":"scalar","defaultRaw":"CURRENT_TIMESTAMP","getter":false,"setter":false,"type":"Date"},"updatedAt":{"name":"updatedAt","reference":"scalar","defaultRaw":"CURRENT_TIMESTAMP","nullable":true,"getter":false,"setter":false,"type":"Date"}},"hooks":{},"filters":{},"primaryKeys":["id"],"indexes":[],"uniques":[],"path":"./src/entities/BaseEntity.entity.ts","abstract":true,"constructorParams":[],"toJsonParams":[],"useCache":true,"compositePK":false,"props":[{"name":"id","reference":"scalar","primary":true,"type":"number"},{"name":"idx","reference":"scalar","defaultRaw":"uuid_generate_v4()","getter":false,"setter":false,"type":"string"},{"name":"is_active","reference":"scalar","nullable":false,"default":true,"getter":false,"setter":false,"type":"boolean"},{"name":"is_obsolete","reference":"scalar","nullable":false,"default":false,"getter":false,"setter":false,"type":"boolean"},{"name":"createdAt","reference":"scalar","defaultRaw":"CURRENT_TIMESTAMP","getter":false,"setter":false,"type":"Date"},{"name":"updatedAt","reference":"scalar","defaultRaw":"CURRENT_TIMESTAMP","nullable":true,"getter":false,"setter":false,"type":"Date"}]},"origin":"./src/entities/BaseEntity.entity.ts","hash":"b9520a8bf13250727b2befec6eb09d66","version":"4.1.0"}
