{"data":{"_id":7000,"properties":{"points":{"name":"points","kind":"scalar","getter":false,"setter":false,"type":"number","array":false,"runtimeType":"number"},"amount":{"name":"amount","kind":"scalar","getter":false,"setter":false,"columnTypes":["numeric(9,2)"],"type":"string","array":false,"runtimeType":"string"},"user":{"name":"user","kind":"m:1","cascade":["persist"],"index":true,"owner":true,"type":"User","array":false,"runtimeType":"{ id: number; } & import\"/home/rubin/personal/typescript/ultimate-nest/node_modules/.pnpm/@mikro-orm+postgresql@6.4.3_@mikro-orm+core@6.4.3/node_modules/@mikro-orm/postgresql/index\".Reference<User & object>","ref":true}},"primaryKeys":[],"filters":{},"hooks":{},"indexes":[],"uniques":[],"className":"PointRedemptionLog","path":"./dist/entities/points-redemption-log.entity.js","name":"PointRedemptionLog","abstract":false,"internal":true,"constructorParams":["partial"],"toJsonParams":[],"extends":"BaseEntity","useCache":true,"collection":"point_redemption_log"},"origin":"./dist/entities/points-redemption-log.entity.js","hash":"d537fbde084ec3c024b6694fd295c2f6","version":"6.4.3"}
